undocinclude/__init__.py
undocinclude/directives.py
undocinclude/extension.py
undocinclude-0.2.0.dist-info/LICENSE.md
undocinclude-0.2.0.dist-info/METADATA
undocinclude-0.2.0.dist-info/WHEEL
undocinclude-0.2.0.dist-info/top_level.txt
undocinclude-0.2.0.dist-info/RECORD
