Metadata-Version: 2.1
Name: undocinclude
Version: 0.2.0
Summary: Sphinx' literalinclude, but without docstrings
Home-page: https://github.com/SamWilsn/undocinclude
Author: Sam Wilson
Author-email: sam.wilson@mesh.xyz
License: UNKNOWN
Platform: UNKNOWN
Classifier: License :: OSI Approved :: BSD License
Requires-Python: >=3.7
License-File: LICENSE.md
Requires-Dist: docutils (<0.18,>=0.14)
Requires-Dist: sphinx (>=4.0)
